seisvis/__init__.py
seisvis/data_cube.py
seisvis/plot1d.py
seisvis/plot2d.py
seisvis/plot3d.py
seisvis/plot_config.py
seisvis/opendtect_colormaps/ColTabs
seisvis/opendtect_colormaps/__init__.py
seisvis/opendtect_colormaps/src.py
seisvis-0.2.2.dist-info/licenses/LICENSE
seisvis-0.2.2.dist-info/METADATA
seisvis-0.2.2.dist-info/WHEEL
seisvis-0.2.2.dist-info/top_level.txt
seisvis-0.2.2.dist-info/RECORD
