Metadata-Version: 2.4
Name: seisvis
Version: 0.2.2
Summary: Seismic data visualization and plotting utilities
Home-page: https://github.com/PangJiutian/Seisvis
Author: Qi Pang
Author-email: pangjiutian@gmail.com
Classifier: Programming Language :: Python :: 3
Classifier: License :: OSI Approved :: MIT License
Classifier: Operating System :: OS Independent
Requires-Python: >=3.8
License-File: LICENSE
Requires-Dist: numpy
Requires-Dist: scipy
Requires-Dist: matplotlib
Dynamic: license-file
